mdisk/__init__.py
mdisk/api.py
mdisk/mdisk.py
mdisk-0.0.1.dist-info/LICENSE
mdisk-0.0.1.dist-info/METADATA
mdisk-0.0.1.dist-info/WHEEL
mdisk-0.0.1.dist-info/entry_points.txt
mdisk-0.0.1.dist-info/top_level.txt
mdisk-0.0.1.dist-info/RECORD
