Metadata-Version: 2.1
Name: mdisk
Version: 0.0.1
Summary: Unofficial python api wrapper from https://mdisk.me
Home-page: https://github.com/HeimanPictures/mdisk
Author: Akkil
Author-email: heimanpicturesofficial@gmail.com
License: UNKNOWN
Keywords: api mdisk video hosting unlimited
Platform: UNKNOWN
Classifier: Development Status :: 3 - Alpha
Classifier: Programming Language :: Python :: 3
Classifier: Intended Audience :: Developers
Classifier: Natural Language :: English
Classifier: Operating System :: OS Independent
License-File: LICENSE
Requires-Dist: requests
Requires-Dist: click
